example/__init__.py
example/multitest.yaml
nmrbox_iptables/__init__.py
nmrbox_iptables/iptables.py
nmrbox_iptables/scripts/__init__.py
nmrbox_iptables/scripts/addrule.py
nmrbox_iptables-2.2.2.dist-info/METADATA
nmrbox_iptables-2.2.2.dist-info/WHEEL
nmrbox_iptables-2.2.2.dist-info/entry_points.txt
nmrbox_iptables-2.2.2.dist-info/top_level.txt
nmrbox_iptables-2.2.2.dist-info/RECORD
