Metadata-Version: 2.1
Name: nmrbox-iptables
Version: 2.2.2
Summary: Utility for setting iptables
Author: Gerard
Author-email: gweatherby@uchc.edu
License: MIT license
Requires-Dist: python-iptables
Requires-Dist: pyyaml
